arithmaticpy/__init__.py
arithmaticpy/vlad.py
arithmaticpy-0.1.3.dist-info/METADATA
arithmaticpy-0.1.3.dist-info/WHEEL
arithmaticpy-0.1.3.dist-info/top_level.txt
arithmaticpy-0.1.3.dist-info/RECORD
