Metadata-Version: 2.1
Name: arithmaticpy
Version: 0.1.3
Summary: Simple Arithmatic Python Library
Home-page: https://github.com/vladyslavnUA/arithmaticpy
Author: vladyslavn
License: MIT
Platform: UNKNOWN
